exercises/__init__.py
exercises/ThirdChapter/__init__.py
exercises/ThirdChapter/commands.py
exercises/ThirdChapter/csix.py
utils/__init__.py
utils/cli.py
utils/configuration.py
utils/log.py
utils/math.py
beersolver-0.1.1.dist-info/LICENSE
beersolver-0.1.1.dist-info/METADATA
beersolver-0.1.1.dist-info/WHEEL
beersolver-0.1.1.dist-info/entry_points.txt
beersolver-0.1.1.dist-info/top_level.txt
beersolver-0.1.1.dist-info/RECORD
