Metadata-Version: 2.1
Name: beersolver
Version: 0.1.1
Summary: A script for solving vector mechanics Ferdinand P. Beer proposed exercises.
Home-page: https://github.com/Nepo26/Beersolver
Author: Henrique Nepomuceno
Author-email: nepo26.hn@protonmail.com
License: GNU GPLv3
Platform: UNKNOWN
License-File: LICENSE
Requires-Dist: Click
